LICENSE
concurrenttools/__init__.py
concurrenttools/py.typed
python_concurrenttools-0.1.3.1.dist-info/LICENSE
python_concurrenttools-0.1.3.1.dist-info/METADATA
python_concurrenttools-0.1.3.1.dist-info/WHEEL
python_concurrenttools-0.1.3.1.dist-info/RECORD
