Metadata-Version: 2.1
Name: python-concurrenttools
Version: 0.1.3.1
Summary: Python concurrent tools.
Home-page: https://github.com/ChenyangGao/python-modules/tree/main/python-concurrenttools
License: MIT
Keywords: concurrent,tools
Author: ChenyangGao
Author-email: wosiwujm@gmail.com
Requires-Python: >=3.12,<4.0
Classifier: Development Status :: 5 - Production/Stable
Classifier: Intended Audience :: Developers
Classifier: License :: OSI Approved :: MIT License
Classifier: Operating System :: OS Independent
Classifier: Programming Language :: Python
Classifier: Programming Language :: Python :: 3
Classifier: Programming Language :: Python :: 3.12
Classifier: Programming Language :: Python :: 3.13
Classifier: Programming Language :: Python :: 3 :: Only
Classifier: Topic :: Software Development
Classifier: Topic :: Software Development :: Libraries
Classifier: Topic :: Software Development :: Libraries :: Python Modules
Requires-Dist: python-argtools (>=0.0.2)
Requires-Dist: python-asynctools (>=0.1.3)
Requires-Dist: python-decotools (>=0.0.2)
Project-URL: Repository, https://github.com/ChenyangGao/python-modules/tree/main/python-concurrenttools
